djangocms_pai_custom_elements/__init__.py
djangocms_pai_custom_elements/admin.py
djangocms_pai_custom_elements/apps.py
djangocms_pai_custom_elements/cms_plugins.py
djangocms_pai_custom_elements/models.py
djangocms_pai_custom_elements/migrations/0001_initial.py
djangocms_pai_custom_elements/migrations/__init__.py
djangocms_pai_custom_elements/templates/custom_elements/elements/base.html
djangocms_pai_custom_elements/templates/custom_elements/elements/custom-element.html
djangocms_pai_custom_elements/templates/custom_elements/elements/generic-custom-element.html
djangocms_pai_custom_elements/templates/djangocms_pai_custom_elements/elements/base.html
djangocms_pai_custom_elements/templates/djangocms_pai_custom_elements/elements/custom-element.html
djangocms_pai_custom_elements/templates/djangocms_pai_custom_elements/elements/generic-custom-element.html
djangocms_pai_custom_elements-0.0.2.dist-info/AUTHORS.rst
djangocms_pai_custom_elements-0.0.2.dist-info/LICENSE.txt
djangocms_pai_custom_elements-0.0.2.dist-info/METADATA
djangocms_pai_custom_elements-0.0.2.dist-info/WHEEL
djangocms_pai_custom_elements-0.0.2.dist-info/top_level.txt
djangocms_pai_custom_elements-0.0.2.dist-info/RECORD
